{
  "root": "card",
  "state": {},
  "elements": {
    "card": {
      "type": "Card",
      "props": {
        "title": "Repo Pulse — 2026-06-11"
      },
      "children": [
        "stack-main"
      ]
    },
    "stack-main": {
      "type": "Stack",
      "props": {
        "direction": "vertical",
        "gap": "md"
      },
      "children": [
        "repo-link",
        "sep1",
        "metrics-stack",
        "sep2",
        "stargazers-stack"
      ]
    },
    "repo-link": {
      "type": "StoryLink",
      "props": {
        "title": "aaronjmars/MiroShark",
        "href": "https://github.com/aaronjmars/MiroShark",
        "source": "GitHub"
      }
    },
    "sep1": {
      "type": "Separator",
      "props": {
        "orientation": "horizontal"
      }
    },
    "metrics-stack": {
      "type": "Stack",
      "props": {
        "direction": "horizontal",
        "gap": "lg"
      },
      "children": [
        "stat-stars",
        "stat-forks"
      ]
    },
    "stat-stars": {
      "type": "Stat",
      "props": {
        "label": "Stars",
        "value": "1246",
        "delta": "+2",
        "trend": "up"
      }
    },
    "stat-forks": {
      "type": "Stat",
      "props": {
        "label": "Forks",
        "value": "263",
        "delta": "+0",
        "trend": "neutral"
      }
    },
    "sep2": {
      "type": "Separator",
      "props": {
        "orientation": "horizontal"
      }
    },
    "stargazers-stack": {
      "type": "Stack",
      "props": {
        "direction": "vertical",
        "gap": "md"
      },
      "children": [
        "stargazers-heading",
        "stargazer-1",
        "stargazer-2"
      ]
    },
    "stargazers-heading": {
      "type": "Heading",
      "props": {
        "text": "New Stargazers",
        "level": "h3"
      }
    },
    "stargazer-1": {
      "type": "Stack",
      "props": {
        "direction": "horizontal",
        "gap": "md"
      },
      "children": [
        "sg1-link",
        "sg1-info"
      ]
    },
    "sg1-link": {
      "type": "Link",
      "props": {
        "label": "github.com/AIRzZ90",
        "href": "https://github.com/AIRzZ90"
      }
    },
    "sg1-info": {
      "type": "Text",
      "props": {
        "text": "0 followers · 1 repo",
        "variant": "caption"
      }
    },
    "stargazer-2": {
      "type": "Stack",
      "props": {
        "direction": "horizontal",
        "gap": "md"
      },
      "children": [
        "sg2-link",
        "sg2-info"
      ]
    },
    "sg2-link": {
      "type": "Link",
      "props": {
        "label": "github.com/AmeanAF",
        "href": "https://github.com/AmeanAF"
      }
    },
    "sg2-info": {
      "type": "Text",
      "props": {
        "text": "8 followers · 3 repos",
        "variant": "caption"
      }
    }
  }
}
