{
  "root": "card_root",
  "state": {},
  "elements": {
    "card_root": {
      "type": "Card",
      "props": {
        "title": "Tweet Rewards — 2026-05-01"
      },
      "children": [
        "main_stack"
      ]
    },
    "main_stack": {
      "type": "Stack",
      "props": {
        "direction": "vertical",
        "gap": "md"
      },
      "children": [
        "budget_heading",
        "budget_stat",
        "separator1",
        "tweet1_stack",
        "sep_1_2",
        "tweet2_stack",
        "sep_2_3",
        "tweet3_stack",
        "sep_3_4",
        "tweet4_stack",
        "separator2",
        "total_text"
      ]
    },
    "budget_heading": {
      "type": "Heading",
      "props": {
        "text": "Budget",
        "level": "h3"
      }
    },
    "budget_stat": {
      "type": "Stat",
      "props": {
        "value": "$10.00 in $MIROSHARK on Base"
      }
    },
    "separator1": {
      "type": "Separator",
      "props": {}
    },
    "tweet1_stack": {
      "type": "Stack",
      "props": {
        "direction": "vertical",
        "gap": "sm"
      },
      "children": [
        "tweet1_number",
        "tweet1_author",
        "tweet1_amount",
        "tweet1_score",
        "tweet1_desc",
        "tweet1_link"
      ]
    },
    "tweet1_number": {
      "type": "Text",
      "props": {
        "text": "1.",
        "variant": "muted"
      }
    },
    "tweet1_author": {
      "type": "Text",
      "props": {
        "text": "x.com/ZenRacc00n",
        "variant": "lead"
      }
    },
    "tweet1_amount": {
      "type": "Stat",
      "props": {
        "value": "$4.10 in $MIROSHARK"
      }
    },
    "tweet1_score": {
      "type": "Badge",
      "props": {
        "text": "score: 16"
      }
    },
    "tweet1_desc": {
      "type": "Text",
      "props": {
        "text": "$MIROSHARK has 869 Stars on GitHub — alpha play with clean technicals"
      }
    },
    "tweet1_link": {
      "type": "Link",
      "props": {
        "label": "View tweet",
        "href": "https://x.com/ZenRacc00n/status/2049807229012853093"
      }
    },
    "sep_1_2": {
      "type": "Separator",
      "props": {}
    },
    "tweet2_stack": {
      "type": "Stack",
      "props": {
        "direction": "vertical",
        "gap": "sm"
      },
      "children": [
        "tweet2_number",
        "tweet2_author",
        "tweet2_amount",
        "tweet2_score",
        "tweet2_desc",
        "tweet2_link"
      ]
    },
    "tweet2_number": {
      "type": "Text",
      "props": {
        "text": "2.",
        "variant": "muted"
      }
    },
    "tweet2_author": {
      "type": "Text",
      "props": {
        "text": "x.com/cybercelos",
        "variant": "lead"
      }
    },
    "tweet2_amount": {
      "type": "Stat",
      "props": {
        "value": "$3.59 in $MIROSHARK"
      }
    },
    "tweet2_score": {
      "type": "Badge",
      "props": {
        "text": "score: 14"
      }
    },
    "tweet2_desc": {
      "type": "Text",
      "props": {
        "text": "Dev is big, project is huge — calling the Chinese buyer wave early"
      }
    },
    "tweet2_link": {
      "type": "Link",
      "props": {
        "label": "View tweet",
        "href": "https://x.com/cybercelos/status/2049978900663640260"
      }
    },
    "sep_2_3": {
      "type": "Separator",
      "props": {}
    },
    "tweet3_stack": {
      "type": "Stack",
      "props": {
        "direction": "vertical",
        "gap": "sm"
      },
      "children": [
        "tweet3_number",
        "tweet3_author",
        "tweet3_amount",
        "tweet3_score",
        "tweet3_desc",
        "tweet3_link"
      ]
    },
    "tweet3_number": {
      "type": "Text",
      "props": {
        "text": "3.",
        "variant": "muted"
      }
    },
    "tweet3_author": {
      "type": "Text",
      "props": {
        "text": "x.com/DaMikey23",
        "variant": "lead"
      }
    },
    "tweet3_amount": {
      "type": "Stat",
      "props": {
        "value": "$1.28 in $MIROSHARK"
      }
    },
    "tweet3_score": {
      "type": "Badge",
      "props": {
        "text": "score: 5"
      }
    },
    "tweet3_desc": {
      "type": "Text",
      "props": {
        "text": "$MIROSHARK $AEON — pairing the token with the framework"
      }
    },
    "tweet3_link": {
      "type": "Link",
      "props": {
        "label": "View tweet",
        "href": "https://x.com/DaMikey23/status/2049994446628921433"
      }
    },
    "sep_3_4": {
      "type": "Separator",
      "props": {}
    },
    "tweet4_stack": {
      "type": "Stack",
      "props": {
        "direction": "vertical",
        "gap": "sm"
      },
      "children": [
        "tweet4_number",
        "tweet4_author",
        "tweet4_amount",
        "tweet4_score",
        "tweet4_desc",
        "tweet4_link"
      ]
    },
    "tweet4_number": {
      "type": "Text",
      "props": {
        "text": "4.",
        "variant": "muted"
      }
    },
    "tweet4_author": {
      "type": "Text",
      "props": {
        "text": "x.com/Dannyhbrown",
        "variant": "lead"
      }
    },
    "tweet4_amount": {
      "type": "Stat",
      "props": {
        "value": "$1.03 in $MIROSHARK"
      }
    },
    "tweet4_score": {
      "type": "Badge",
      "props": {
        "text": "score: 4"
      }
    },
    "tweet4_desc": {
      "type": "Text",
      "props": {
        "text": "Most based builders I've ever seen, a true honor to support them"
      }
    },
    "tweet4_link": {
      "type": "Link",
      "props": {
        "label": "View tweet",
        "href": "https://x.com/Dannyhbrown/status/2049989410393858446"
      }
    },
    "separator2": {
      "type": "Separator",
      "props": {}
    },
    "total_text": {
      "type": "Text",
      "props": {
        "text": "Total: $10.00 in $MIROSHARK allocated to 4 authors",
        "variant": "lead"
      }
    }
  }
}
