{
  "root": "main_card",
  "state": {},
  "elements": {
    "main_card": {
      "type": "Card",
      "props": {
        "title": "Tweet Rewards — 2026-05-15"
      },
      "children": [
        "budget",
        "sep1",
        "tweets_list",
        "sep2",
        "summary"
      ]
    },
    "budget": {
      "type": "Stat",
      "props": {
        "label": "Budget (Base)",
        "value": "$10.00 in $MIROSHARK"
      }
    },
    "sep1": {
      "type": "Separator",
      "props": {}
    },
    "tweets_list": {
      "type": "Stack",
      "props": {
        "direction": "vertical",
        "gap": "lg"
      },
      "children": [
        "tweet_1",
        "tweet_2",
        "tweet_3",
        "tweet_4",
        "tweet_5"
      ]
    },
    "tweet_1": {
      "type": "Stack",
      "props": {
        "direction": "vertical",
        "gap": "sm"
      },
      "children": [
        "tweet_1_meta",
        "tweet_1_desc",
        "tweet_1_link"
      ]
    },
    "tweet_1_meta": {
      "type": "Stack",
      "props": {
        "direction": "horizontal",
        "gap": "md"
      },
      "children": [
        "tweet_1_author",
        "tweet_1_amount",
        "tweet_1_score"
      ]
    },
    "tweet_1_author": {
      "type": "Text",
      "props": {
        "text": "x.com/_THOR_ASGARD"
      }
    },
    "tweet_1_amount": {
      "type": "Badge",
      "props": {
        "text": "$3.33 in $MIROSHARK"
      }
    },
    "tweet_1_score": {
      "type": "Badge",
      "props": {
        "text": "score: 2"
      }
    },
    "tweet_1_desc": {
      "type": "Text",
      "props": {
        "text": "AI agent simulation of narratives, FUD, and liquidity shocks via hundreds of agents mimicking traders and regulators"
      }
    },
    "tweet_1_link": {
      "type": "Link",
      "props": {
        "label": "View tweet",
        "href": "https://x.com/_THOR_ASGARD/status/2054779585720627355"
      }
    },
    "tweet_2": {
      "type": "Stack",
      "props": {
        "direction": "vertical",
        "gap": "sm"
      },
      "children": [
        "tweet_2_meta",
        "tweet_2_desc",
        "tweet_2_link"
      ]
    },
    "tweet_2_meta": {
      "type": "Stack",
      "props": {
        "direction": "horizontal",
        "gap": "md"
      },
      "children": [
        "tweet_2_author",
        "tweet_2_amount",
        "tweet_2_score"
      ]
    },
    "tweet_2_author": {
      "type": "Text",
      "props": {
        "text": "x.com/cybercelos"
      }
    },
    "tweet_2_amount": {
      "type": "Badge",
      "props": {
        "text": "$1.67 in $MIROSHARK"
      }
    },
    "tweet_2_score": {
      "type": "Badge",
      "props": {
        "text": "score: 1"
      }
    },
    "tweet_2_desc": {
      "type": "Text",
      "props": {
        "text": "Bullish $MIROSHARK take"
      }
    },
    "tweet_2_link": {
      "type": "Link",
      "props": {
        "label": "View tweet",
        "href": "https://x.com/cybercelos/status/2055048630218998184"
      }
    },
    "tweet_3": {
      "type": "Stack",
      "props": {
        "direction": "vertical",
        "gap": "sm"
      },
      "children": [
        "tweet_3_meta",
        "tweet_3_desc",
        "tweet_3_link"
      ]
    },
    "tweet_3_meta": {
      "type": "Stack",
      "props": {
        "direction": "horizontal",
        "gap": "md"
      },
      "children": [
        "tweet_3_author",
        "tweet_3_amount",
        "tweet_3_score"
      ]
    },
    "tweet_3_author": {
      "type": "Text",
      "props": {
        "text": "x.com/_THOR_ASGARD"
      }
    },
    "tweet_3_amount": {
      "type": "Badge",
      "props": {
        "text": "$1.67 in $MIROSHARK"
      }
    },
    "tweet_3_score": {
      "type": "Badge",
      "props": {
        "text": "score: 1"
      }
    },
    "tweet_3_desc": {
      "type": "Text",
      "props": {
        "text": "Crypto simulation engine framing — $AEON synergy"
      }
    },
    "tweet_3_link": {
      "type": "Link",
      "props": {
        "label": "View tweet",
        "href": "https://x.com/_THOR_ASGARD/status/2054779593865970068"
      }
    },
    "tweet_4": {
      "type": "Stack",
      "props": {
        "direction": "vertical",
        "gap": "sm"
      },
      "children": [
        "tweet_4_meta",
        "tweet_4_desc",
        "tweet_4_link"
      ]
    },
    "tweet_4_meta": {
      "type": "Stack",
      "props": {
        "direction": "horizontal",
        "gap": "md"
      },
      "children": [
        "tweet_4_author",
        "tweet_4_amount",
        "tweet_4_score"
      ]
    },
    "tweet_4_author": {
      "type": "Text",
      "props": {
        "text": "x.com/WazzupCrypto"
      }
    },
    "tweet_4_amount": {
      "type": "Badge",
      "props": {
        "text": "$1.67 in $MIROSHARK"
      }
    },
    "tweet_4_score": {
      "type": "Badge",
      "props": {
        "text": "score: 1"
      }
    },
    "tweet_4_desc": {
      "type": "Text",
      "props": {
        "text": "Bullish $MIROSHARK call"
      }
    },
    "tweet_4_link": {
      "type": "Link",
      "props": {
        "label": "View tweet",
        "href": "https://x.com/WazzupCrypto/status/2055071697272005012"
      }
    },
    "tweet_5": {
      "type": "Stack",
      "props": {
        "direction": "vertical",
        "gap": "sm"
      },
      "children": [
        "tweet_5_meta",
        "tweet_5_desc",
        "tweet_5_link"
      ]
    },
    "tweet_5_meta": {
      "type": "Stack",
      "props": {
        "direction": "horizontal",
        "gap": "md"
      },
      "children": [
        "tweet_5_author",
        "tweet_5_amount",
        "tweet_5_score"
      ]
    },
    "tweet_5_author": {
      "type": "Text",
      "props": {
        "text": "x.com/NexlifyCoin"
      }
    },
    "tweet_5_amount": {
      "type": "Badge",
      "props": {
        "text": "$1.66 in $MIROSHARK"
      }
    },
    "tweet_5_score": {
      "type": "Badge",
      "props": {
        "text": "score: 1"
      }
    },
    "tweet_5_desc": {
      "type": "Text",
      "props": {
        "text": "$MIROSHARK token run list"
      }
    },
    "tweet_5_link": {
      "type": "Link",
      "props": {
        "label": "View tweet",
        "href": "https://x.com/NexlifyCoin/status/2055049582753779730"
      }
    },
    "sep2": {
      "type": "Separator",
      "props": {}
    },
    "summary": {
      "type": "Text",
      "props": {
        "text": "Total: $10.00 in $MIROSHARK allocated to 5 tweets (4 authors)",
        "variant": "lead"
      }
    }
  }
}
